seqmetric/__init__.py
seqmetric/reporters.py
seqmetric/scheme.py
seqmetric/test_py.py
seqmetric/metrics/__init__.py
seqmetric/metrics/sequence_labeling.py
seqmetric/metrics/spo_labeling.py
seqmetric/metrics/v1.py
seqmetric-0.1.2.dist-info/METADATA
seqmetric-0.1.2.dist-info/WHEEL
seqmetric-0.1.2.dist-info/top_level.txt
seqmetric-0.1.2.dist-info/RECORD
